pyoload.py
pyoload-3.0.0.dist-info/LICENSE
pyoload-3.0.0.dist-info/METADATA
pyoload-3.0.0.dist-info/WHEEL
pyoload-3.0.0.dist-info/top_level.txt
pyoload-3.0.0.dist-info/RECORD
