Metadata-Version: 2.2
Name: pyoload
Version: 3.0.0
Summary: Runtime typechecking debugging module.
Author-email: Engon Ken Morel <engonken8@gmail.com>
Maintainer-email: Engon Ken Morel <engonken8@gmail.com>
License: Copyright 2024 ken-morel
Project-URL: Homepage, https://github.com/ken-morel/pyoload
Project-URL: Repository, https://github.com/ken-morel/pyoload.git
Project-URL: Issues, https://github.com/ken-morel/pyoload/issues
Keywords: annotations,pyoload,debug
Classifier: Development Status :: 4 - Beta
Classifier: Intended Audience :: Developers
Classifier: License :: OSI Approved :: MIT License
Classifier: Programming Language :: Python :: 3
Classifier: Programming Language :: Python :: 3.10
Classifier: Programming Language :: Python :: 3.11
Classifier: Programming Language :: Python :: 3.12
Classifier: Programming Language :: Python :: 3.13
License-File: LICENSE
